{
	"info": {
		"_postman_id": "a1b2c3d4-e5f6-4g7h-8i9j-k1l2m3n4o5p6",
		"name": "GlucoWizard API",
		"description": "API collection for GlucoWizard - Diabetic analysis and AI reporting.",
		"schema": "https://schema.getpostman.com/json/collection/v2.1.0/collection.json"
	},
	"item": [
		{
			"name": "Authentication",
			"item": [
				{
					"name": "Register",
					"request": {
						"method": "POST",
						"header": [],
						"body": {
							"mode": "raw",
							"raw": "{\n    \"username\": \"testuser\",\n    \"email\": \"test@example.com\",\n    \"password\": \"Password123!\",\n    \"password2\": \"Password123!\"\n}",
							"options": {
								"raw": {
									"language": "json"
								}
							}
						},
						"url": {
							"raw": "{{baseUrl}}/users/register/",
							"host": [
								"{{baseUrl}}"
							],
							"path": [
								"users",
								"register",
								""
							]
						}
					},
					"response": []
				},
				{
					"name": "Login",
					"request": {
						"method": "POST",
						"header": [],
						"body": {
							"mode": "raw",
							"raw": "{\n    \"email\": \"test@example.com\",\n    \"password\": \"Password123!\"\n}",
							"options": {
								"raw": {
									"language": "json"
								}
							}
						},
						"url": {
							"raw": "{{baseUrl}}/users/login/",
							"host": [
								"{{baseUrl}}"
							],
							"path": [
								"users",
								"login",
								""
							]
						}
					},
					"response": []
				},
				{
					"name": "Refresh Token",
					"request": {
						"method": "POST",
						"header": [],
						"body": {
							"mode": "raw",
							"raw": "{\n    \"refresh_token\": \"<your_refresh_token>\"\n}",
							"options": {
								"raw": {
									"language": "json"
								}
							}
						},
						"url": {
							"raw": "{{baseUrl}}/users/refresh-token/",
							"host": [
								"{{baseUrl}}"
							],
							"path": [
								"users",
								"refresh-token",
								""
							]
						}
					},
					"response": []
				},
				{
					"name": "Forgot Password",
					"request": {
						"method": "POST",
						"header": [],
						"body": {
							"mode": "raw",
							"raw": "{\n    \"email\": \"test@example.com\"\n}",
							"options": {
								"raw": {
									"language": "json"
								}
							}
						},
						"url": {
							"raw": "{{baseUrl}}/users/forgot-password/",
							"host": [
								"{{baseUrl}}"
							],
							"path": [
								"users",
								"forgot-password",
								""
							]
						}
					},
					"response": []
				},
				{
					"name": "Update Password",
					"request": {
						"auth": {
							"type": "bearer",
							"bearer": [
								{
									"key": "token",
									"value": "{{accessToken}}",
									"type": "string"
								}
							]
						},
						"method": "POST",
						"header": [],
						"body": {
							"mode": "raw",
							"raw": "{\n    \"password\": \"NewPassword123!\"\n}",
							"options": {
								"raw": {
									"language": "json"
								}
							}
						},
						"url": {
							"raw": "{{baseUrl}}/users/update-password/",
							"host": [
								"{{baseUrl}}"
							],
							"path": [
								"users",
								"update-password",
								""
							]
						}
					},
					"response": []
				},
				{
					"name": "Change Password",
					"request": {
						"auth": {
							"type": "bearer",
							"bearer": [
								{
									"key": "token",
									"value": "{{accessToken}}",
									"type": "string"
								}
							]
						},
						"method": "POST",
						"header": [],
						"body": {
							"mode": "raw",
							"raw": "{\n    \"old_password\": \"OldPassword123!\",\n    \"new_password\": \"NewPassword123!\"\n}",
							"options": {
								"raw": {
									"language": "json"
								}
							}
						},
						"url": {
							"raw": "{{baseUrl}}/users/change-password/",
							"host": [
								"{{baseUrl}}"
							],
							"path": [
								"users",
								"change-password",
								""
							]
						}
					},
					"response": []
				},
				{
					"name": "Google Auth Redirect",
					"request": {
						"method": "GET",
						"header": [],
						"url": {
							"raw": "{{baseUrl}}/users/google-auth/?redirect_to=http://localhost:3000/auth/callback",
							"host": [
								"{{baseUrl}}"
							],
							"path": [
								"users",
								"google-auth",
								""
							],
							"query": [
								{
									"key": "redirect_to",
									"value": "http://localhost:3000/auth/callback"
								}
							]
						}
					},
					"response": []
				},
				{
					"name": "Google Callback",
					"request": {
						"method": "GET",
						"header": [],
						"url": {
							"raw": "{{baseUrl}}/users/google-callback/?code=<auth_code_from_google>",
							"host": [
								"{{baseUrl}}"
							],
							"path": [
								"users",
								"google-callback",
								""
							],
							"query": [
								{
									"key": "code",
									"value": "<auth_code_from_google>"
								}
							]
						}
					},
					"response": []
				}
			]
		},
		{
			"name": "Profile",
			"item": [
				{
					"name": "Get My Info",
					"request": {
						"auth": {
							"type": "bearer",
							"bearer": [
								{
									"key": "token",
									"value": "{{accessToken}}",
									"type": "string"
								}
							]
						},
						"method": "GET",
						"header": [],
						"url": {
							"raw": "{{baseUrl}}/users/me/",
							"host": [
								"{{baseUrl}}"
							],
							"path": [
								"users",
								"me",
								""
							]
						}
					},
					"response": []
				},
				{
					"name": "Upload Avatar",
					"request": {
						"auth": {
							"type": "bearer",
							"bearer": [
								{
									"key": "token",
									"value": "{{accessToken}}",
									"type": "string"
								}
							]
						},
						"method": "POST",
						"header": [],
						"body": {
							"mode": "formdata",
							"formdata": [
								{
									"key": "avatar",
									"type": "file",
									"src": []
								}
							]
						},
						"url": {
							"raw": "{{baseUrl}}/users/upload-avatar/",
							"host": [
								"{{baseUrl}}"
							],
							"path": [
								"users",
								"upload-avatar",
								""
							]
						}
					},
					"response": []
				}
			]
		},
		{
			"name": "Reports",
			"item": [
				{
					"name": "Report Stats",
					"request": {
						"auth": {
							"type": "bearer",
							"bearer": [
								{
									"key": "token",
									"value": "{{accessToken}}",
									"type": "string"
								}
							]
						},
						"method": "GET",
						"header": [],
						"url": {
							"raw": "{{baseUrl}}/reports/stats/?period=week",
							"host": [
								"{{baseUrl}}"
							],
							"path": [
								"reports",
								"stats",
								""
							],
							"query": [
								{
									"key": "period",
									"value": "week",
									"description": "week or month"
								}
							]
						}
					},
					"response": []
				},
				{
					"name": "List Reports",
					"request": {
						"auth": {
							"type": "bearer",
							"bearer": [
								{
									"key": "token",
									"value": "{{accessToken}}",
									"type": "string"
								}
							]
						},
						"method": "GET",
						"header": [],
						"url": {
							"raw": "{{baseUrl}}/reports/?page=1&page_size=10",
							"host": [
								"{{baseUrl}}"
							],
							"path": [
								"reports",
								""
							],
							"query": [
								{
									"key": "page",
									"value": "1"
								},
								{
									"key": "page_size",
									"value": "10"
								}
							]
						}
					},
					"response": []
				},
				{
					"name": "Create Report",
					"request": {
						"auth": {
							"type": "bearer",
							"bearer": [
								{
									"key": "token",
									"value": "{{accessToken}}",
									"type": "string"
								}
							]
						},
						"method": "POST",
						"header": [],
						"body": {
							"mode": "formdata",
							"formdata": [
								{
									"key": "diabetic_values",
									"value": "{\n    \"bolus_ratio\": [\n        {\n            \"start_time\": \"06:00\",\n            \"end_time\": \"11:59\",\n            \"insulin\": 1,\n            \"carbs\": 10\n        },\n        {\n            \"start_time\": \"12:00\",\n            \"end_time\": \"23:59\",\n            \"insulin\": 1,\n            \"carbs\": 12\n        }\n    ],\n    \"basal_rates\": [\n        {\n            \"start_time\": \"00:00\",\n            \"end_time\": \"05:59\",\n            \"rate\": 0.8\n        },\n        {\n            \"start_time\": \"06:00\",\n            \"end_time\": \"23:59\",\n            \"rate\": 1.0\n        }\n    ],\n    \"correction_factors\": [\n        {\n            \"start_time\": \"00:00\",\n            \"end_time\": \"11:59\",\n            \"correction_factor\": 50\n        },\n        {\n            \"start_time\": \"12:00\",\n            \"end_time\": \"23:59\",\n            \"correction_factor\": 45\n        }\n    ]\n}",
									"type": "text"
								},
								{
									"key": "pdf_file",
									"type": "file",
									"src": []
								}
							]
						},
						"url": {
							"raw": "{{baseUrl}}/reports/create/",
							"host": [
								"{{baseUrl}}"
							],
							"path": [
								"reports",
								"create",
								""
							]
						}
					},
					"response": []
				},
				{
					"name": "Report Detail",
					"request": {
						"auth": {
							"type": "bearer",
							"bearer": [
								{
									"key": "token",
									"value": "{{accessToken}}",
									"type": "string"
								}
							]
						},
						"method": "GET",
						"header": [],
						"url": {
							"raw": "{{baseUrl}}/reports/<report_id>/",
							"host": [
								"{{baseUrl}}"
							],
							"path": [
								"reports",
								"<report_id>",
								""
							]
						}
					},
					"response": []
				}
			]
		}
	],
	"event": [
		{
			"listen": "prerequest",
			"script": {
				"type": "text/javascript",
				"exec": [
					""
				]
			}
		},
		{
			"listen": "test",
			"script": {
				"type": "text/javascript",
				"exec": [
					""
				]
			}
		}
	],
	"variable": [
		{
			"key": "baseUrl",
			"value": "http://localhost:8000",
			"type": "string"
		},
		{
			"key": "accessToken",
			"value": "",
			"type": "string"
		}
	]
}